BBData/__init__.py
BBData/config.py
BBData/lib.py
BBData/reader_utils.py
BBData/saver_utils.py
BBData/tools.py
BBData/utils.py
Jijin_data-0.5.0.dist-info/LICENSE
Jijin_data-0.5.0.dist-info/METADATA
Jijin_data-0.5.0.dist-info/WHEEL
Jijin_data-0.5.0.dist-info/top_level.txt
Jijin_data-0.5.0.dist-info/RECORD
