Metadata-Version: 2.1
Name: Jijin-data
Version: 0.5.0
Summary: data api
Home-page: https://oa.csc.com.cn
Author: wangcc
Author-email: 705190651@qq.com
License: UNKNOWN
Platform: UNKNOWN
